wattpilot/__init__.py
wattpilot/wattpilotshell.py
wattpilot/ressources/__init__.py
wattpilot/ressources/wattpilot.yaml
wattpilot-0.2.dist-info/LICENSE
wattpilot-0.2.dist-info/METADATA
wattpilot-0.2.dist-info/WHEEL
wattpilot-0.2.dist-info/entry_points.txt
wattpilot-0.2.dist-info/top_level.txt
wattpilot-0.2.dist-info/RECORD
