Metadata-Version: 2.1
Name: wattpilot
Version: 0.2
Summary: Python library to connect to a Fronius Wattpilot Wallbox
Home-page: https://github.com/joscha82/wattpilot
Author: Joscha Arenz
Author-email: joscha@arenz.co
License: MIT License
Project-URL: Bug Reports, https://github.com/joscha82/wattpilot/issues
Project-URL: Source, https://github.com/joscha82/wattpilot
Keywords: wattpilot
Platform: any
Classifier: Development Status :: 3 - Alpha
Classifier: Intended Audience :: Developers
Classifier: License :: OSI Approved :: MIT License
Classifier: Programming Language :: Python :: 3
Classifier: Programming Language :: Python :: 3.10
Classifier: Programming Language :: Python :: 3 :: Only
Requires-Python: >=3.10, <4
License-File: LICENSE
Requires-Dist: websocket-client
Requires-Dist: PyYAML
Requires-Dist: paho-mqtt
